{
 "post_id": "7512025662",
 "title": "2 Refreshing Pools, Close to The Woodlands Mall, Oversized Patios",
 "price": "1244",
 "neighborhood": "25510 Brookhaven Drive, Spring, TX",
 "map_address": "25510 Brookhaven Drive",
 "street_address": "25510 Brookhaven Drive",
 "latitude": "30.1288",
 "longitude": "-95.4239",
 "data_accuracy": "5",
 "posted": "2022-07-22 12:12",
 "updated": "2022-08-01 18:40",
 "repost_dates": "[]",
 "available": "2022-11-30",
 "housing_type": "apartment",
 "bedrooms": "2",
 "bathrooms": "2.0",
 "laundry": "w/d hookups",
 "parking": "off-street parking",
 "sqft": "1001",
 "flooring": "NA",
 "rent_period": "monthly",
 "app_fee": "NA",
 "broker_fee": "NA",
 "cats_ok": "True",
 "dogs_ok": "True",
 "no_smoking": "True",
 "furnished": "NA",
 "wheelchair_access": "True",
 "AC": "True",
 "EV_charging": "NA",
 "posting_body": "['Come discover the best kept secret in the Spring/Woodlands area.,We offer a sophisticated lifestyle with exceptional customer service.', 'We are tucked away, yet close to fine dining, great shopping and countless entertainment.', 'At Imperial Chase you will find yourself surrounded by comfort, convenience and charm.', ',Come by and tour your new home today!', '-Two-Tone Color Scheme', '-Faux Hardwood Floors', '-Large and Abundant Closets', '-2 Interactive Playgrounds', '-Minutes to I-45 + Hardy Toll', '-Upgraded Plumbing Fixtures', '-Laundry Care Center', '-Upgraded Appliance Package', '-Close to Cynthia Woods Pavilion, Lake Conroe + More', '-Built-In Bookshelves', '-Close to The Woodlands Mall', '-Washer/Dryer Connections', 'Call:', 'show contact info', 'For more information, visit us at: <URL>', 'Pricing and availability are subject to change.']",
 "images": "['https://images.craigslist.org/01212_dciLsyHVUgkz_0g8084_600x450.jpg', 'https://images.craigslist.org/00W0W_4T20i3OWZ1pz_0g8084_600x450.jpg', 'https://images.craigslist.org/01717_bDL66htYxCRz_0g8084_600x450.jpg', 'https://images.craigslist.org/00M0M_bZlYVq5e23Yz_0g8084_600x450.jpg', 'https://images.craigslist.org/01111_lRAZwsVojOlz_0g8084_600x450.jpg', 'https://images.craigslist.org/00o0o_9jVgWNl0WMBz_0g8084_600x450.jpg', 'https://images.craigslist.org/00505_k4NORhojJqvz_0g8084_600x450.jpg', 'https://images.craigslist.org/00R0R_bOIM6ZNMloTz_0g8084_600x450.jpg', 'https://images.craigslist.org/00e0e_JfSWxkEj3kz_0jH0cU_600x450.jpg']",
 "url": "https://houston.craigslist.org/apa/d/spring-refreshing-pools-close-to-the/7512025662.html",
 "typology": "NA",
 "GEOID": "48339691900",
 "poverty": "nonpoor",
 "race": "white",
 "white": 89.7,
 "black": 10.3,
 "asian": 0.5,
 "latinx": 20.2,
 "below25k": 5.9,
 "median_income": 87469.0,
 "college": 32.1,
 "foreignborn": 8.2,
 "renteroccupied": 29.9,
 "last10yrs": 1.1,
 "vacancy": 3.9,
 "white_old": 88.2,
 "black_old": 6.0,
 "asian_old": 1.6,
 "latinx_old": 16.6,
 "below25k_old": 4.5,
 "median_income_old": 88975.11,
 "college_old": 27.7,
 "foreignborn_old": 8.3,
 "renteroccupied_old": 22.6,
 "last10yrs_old": 18.5,
 "vacancy_old": 9.4,
 "professional": 67.1,
 "professional_old": 68.9,
 "travel_time": 28.8,
 "travel_time_old": 31.0,
 "new_residents": 25.9,
 "new_residents_old": 34.6,
 "non_english": 11.6,
 "non_english_old": 14.5,
 "avg_rent": 1321.0,
 "avg_rent_old": 1329.23
}