{
 "post_id": 7516286340,
 "title": "single room available for rent",
 "price": 600,
 "neighborhood": "woodlands",
 "map_address": "NA",
 "street_address": "NA",
 "latitude": 30.2127,
 "longitude": -95.4273,
 "data_accuracy": 99,
 "posted": "2022-08-02 02:32",
 "updated": "NA",
 "repost_dates": [],
 "available": "2022-08-02",
 "housing_type": "house",
 "bedrooms": 3,
 "bathrooms": "shared",
 "laundry": "laundry in bldg",
 "parking": "attached garage",
 "sqft": "NA",
 "flooring": "NA",
 "rent_period": "monthly",
 "app_fee": "NA",
 "broker_fee": "NA",
 "cats_ok": "NA",
 "dogs_ok": "NA",
 "no_smoking": true,
 "furnished": "NA",
 "wheelchair_access": "NA",
 "AC": "NA",
 "EV_charging": "NA",
 "posting_body": [
  "Single room available  for rent in woodlands .",
  "Any one intrested text me no calls please."
 ],
 "images": "NA",
 "url": "https://houston.craigslist.org/apa/d/conroe-single-room-available-for-rent/7516286340.html"
}