{
 "post_id": "7483213912",
 "title": "No Fee W11 st /Hudson St Huge 1 Bd flex Duplex w .Roofdeck.929724 0948",
 "price": "7495",
 "neighborhood": "Greenwich Village",
 "map_address": "NA",
 "street_address": "NA",
 "latitude": "40.7255",
 "longitude": "-73.9983",
 "data_accuracy": "22",
 "posted": "2022-08-02 17:47",
 "updated": "2022-08-02 18:02",
 "repost_dates": "['2022-08-02 17:47']",
 "available": "NA",
 "housing_type": "apartment",
 "bedrooms": "1",
 "bathrooms": "1.0",
 "laundry": "w/d in unit",
 "parking": "street parking",
 "sqft": "NA",
 "flooring": "NA",
 "rent_period": "monthly",
 "app_fee": "NA",
 "broker_fee": "NA",
 "cats_ok": "True",
 "dogs_ok": "True",
 "no_smoking": "NA",
 "furnished": "NA",
 "wheelchair_access": "True",
 "AC": "True",
 "EV_charging": "NA",
 "posting_body": "['No Fee A Must See !!!!?', '1BR - Townhouse PENTHOUSE, ENTIRE PRIVATE HUGE FLOOR', 'THROUGH, WITH HUGE PRIVATE ROOF DECK - Eat in Kitchen, Fireplace Prime Greenwich Village Hudson and west 11  Huge 1 bed Duplex with Roofdeck Garden absolutely gorgeous call for video 929 7240948 Huge 1  Bed with office Duplex with Out Door Space Immed Sept  1 929 724 0948', '1 Bed Duplex with Out Door Space roofdeck', 'Listing ID #: 1145', 'Price: $7495', 'Property Type: Apartment', 'Bedrooms: 1.0', 'Bathrooms: 1.0', 'Building Amenities', 'Brownstone', 'Diplomats OK', 'Roof Deck', 'Subway', 'Apartment Amenities', 'Dishwasher', 'Hardwood', 'Light', 'Marble Bath', 'NO FEE', 'Outdoor Space', 'BUILDING & UNIT FEATURES Virtual Doorman NO FEE Outdoor Space Garden roofdeck  Renovated Granite Kitchen Stainless Steel Appliances Microwave Marble Bath Laundry', 'In Unit Multi Level Duplex Hardwood apartment with modern updates features an updated kitchen (with dishwasher), and an in-unit washer and dryer.', 'Additional features include: Details: *private garden *exposed brick *stainless steel appliances *washer/dryer *modern bathroom *modern kitchen *dishwasher *hardwood floors *high ceilings', 'Lenore Paone', 'Phone: 929-724-0948', 'Mobile: 929-724-0948', 'Lenore Paone @ LPRE Real Estate NYC \\xa0 929-724-0948 \\xa0 929-724-0948', 'POSTED BY REALTYMX\u2122', 'To view, call or text Lenore Paone at 929-724-0948', '136Direct to owner Lenore PaoneAlways', 'no fee']",
 "images": "['https://images.craigslist.org/00Y0Y_bllQlyQDdOBz_02H042_600x450.jpg', 'https://images.craigslist.org/00e0e_2NRHqZgkoTPz_02H042_600x450.jpg', 'https://images.craigslist.org/00202_jtA61Mypgq7z_08g0co_600x450.jpg', 'https://images.craigslist.org/00B0B_kxghtd4hd0Wz_06A0co_600x450.jpg', 'https://images.craigslist.org/00t0t_iMVvH6YBabqz_0gw0b1_600x450.jpg', 'https://images.craigslist.org/00v0v_dlmly034syuz_09G06s_600x450.jpg']",
 "url": "https://newyork.craigslist.org/mnh/apa/d/new-york-no-fee-w11-st-hudson-st-huge/7516572738.html",
 "typology": "NA",
 "GEOID": "36061004900",
 "poverty": "nonpoor",
 "race": "white",
 "white": 87.3,
 "black": 3.0,
 "asian": 10.2,
 "latinx": 8.2,
 "below25k": 4.7,
 "median_income": 113871.0,
 "college": 86.0,
 "foreignborn": 23.9,
 "renteroccupied": 75.6,
 "last10yrs": 0.0,
 "vacancy": 14.1,
 "white_old": 87.6,
 "black_old": 3.5,
 "asian_old": 8.5,
 "latinx_old": 5.5,
 "below25k_old": 0.0,
 "median_income_old": 116233.25,
 "college_old": 79.8,
 "foreignborn_old": 17.9,
 "renteroccupied_old": 70.8,
 "last10yrs_old": 0.9,
 "vacancy_old": 13.7,
 "professional": 93.1,
 "professional_old": 89.1,
 "travel_time": 28.2,
 "travel_time_old": 23.5,
 "new_residents": 35.199999999999996,
 "new_residents_old": 47.1,
 "non_english": 24.6,
 "non_english_old": 19.6,
 "avg_rent": 2149.0,
 "avg_rent_old": 2258.62
}