{
 "post_id": "7514198368",
 "title": "Studio Duplex",
 "price": "2335",
 "neighborhood": "Crown Heights",
 "map_address": "NA",
 "street_address": "NA",
 "latitude": "40.671",
 "longitude": "-73.9227",
 "data_accuracy": "99",
 "posted": "2022-07-27 18:26",
 "updated": "NA",
 "repost_dates": "[]",
 "available": "2022-08-01",
 "housing_type": "apartment",
 "bedrooms": "0",
 "bathrooms": "1.5",
 "laundry": "laundry in bldg",
 "parking": "street parking",
 "sqft": "NA",
 "flooring": "NA",
 "rent_period": "monthly",
 "app_fee": "NA",
 "broker_fee": "NA",
 "cats_ok": "True",
 "dogs_ok": "True",
 "no_smoking": "NA",
 "furnished": "NA",
 "wheelchair_access": "NA",
 "AC": "True",
 "EV_charging": "NA",
 "posting_body": "['Studio duplex with 1 full bathroom + half bath.', 'Features:', 'Hardwood floors', 'Central air', 'Stainless steel kitchen with dish washer', 'Laundry in building', 'Located in Crown Heights Near the 3,4 at  Sutter Av and 3,4 at Utica Av.', 'No Fee', 'Good credit and income required', 'Guarantors are welcome', '12 month lease', 'Message or Text me with link to schedule a showing!', '347-495-5448 - Temer']",
 "images": "['https://images.craigslist.org/01111_3WXcEt70TZSz_0CI0t1_600x450.jpg', 'https://images.craigslist.org/01313_dFa3aRtxVK0z_0CI0t1_600x450.jpg', 'https://images.craigslist.org/00f0f_7CUuIVIhbYVz_0t20CI_600x450.jpg', 'https://images.craigslist.org/00h0h_cHJWuDj5CsWz_0t20CI_600x450.jpg']",
 "url": "https://newyork.craigslist.org/brk/apa/d/brooklyn-studio-duplex/7514198368.html",
 "typology": "NA",
 "GEOID": "36047035900",
 "poverty": "poor",
 "race": "black",
 "white": 7.5,
 "black": 81.8,
 "asian": 5.6,
 "latinx": 11.6,
 "below25k": 34.4,
 "median_income": 43309.0,
 "college": 18.3,
 "foreignborn": 30.6,
 "renteroccupied": 88.5,
 "last10yrs": 0.0,
 "vacancy": 6.7,
 "white_old": 2.8,
 "black_old": 90.3,
 "asian_old": 1.3,
 "latinx_old": 8.8,
 "below25k_old": 36.8,
 "median_income_old": 36365.21,
 "college_old": 12.6,
 "foreignborn_old": 41.5,
 "renteroccupied_old": 97.1,
 "last10yrs_old": 1.5,
 "vacancy_old": 14.7,
 "professional": 55.1,
 "professional_old": 40.1,
 "travel_time": 47.4,
 "travel_time_old": 51.6,
 "new_residents": 31.599999999999998,
 "new_residents_old": 51.1,
 "non_english": 20.2,
 "non_english_old": 8.9,
 "avg_rent": 1264.0,
 "avg_rent_old": 1144.78
}