{
 "post_id": "7516189217",
 "title": "Big Bedstuy Studio! $2100!",
 "price": "2100",
 "neighborhood": "Brooklyn",
 "map_address": "448 Jefferson Ave",
 "street_address": "448 Jefferson Ave",
 "latitude": "40.6844",
 "longitude": "-73.94",
 "data_accuracy": "99",
 "posted": "2022-08-02 12:02",
 "updated": "2022-08-02 12:02",
 "repost_dates": "['2022-08-02 12:02']",
 "available": "NA",
 "housing_type": "apartment",
 "bedrooms": "0",
 "bathrooms": "1.0",
 "laundry": "no laundry on site",
 "parking": "street parking",
 "sqft": "NA",
 "flooring": "NA",
 "rent_period": "monthly",
 "app_fee": "NA",
 "broker_fee": "NA",
 "cats_ok": "True",
 "dogs_ok": "True",
 "no_smoking": "NA",
 "furnished": "NA",
 "wheelchair_access": "NA",
 "AC": "True",
 "EV_charging": "NA",
 "posting_body": "['Big Studio apartment in Bedstuy with bright windows and great space!', '9/15 move in!', 'Schedule your showing asap before it\u2019s gone!', 'Call/Text Tim at 717-331-6217']",
 "images": "['https://images.craigslist.org/00W0W_195VryPjFfCz_0CI0t3_600x450.jpg', 'https://images.craigslist.org/00d0d_aOw82QtiYeZz_0CI0t3_600x450.jpg', 'https://images.craigslist.org/00505_8SIPLBDz2Ivz_0CI0t3_600x450.jpg', 'https://images.craigslist.org/00e0e_bLV56mFYiSrz_0CI0t3_600x450.jpg', 'https://images.craigslist.org/00707_lHYQz8Tbu15z_0t20CI_600x450.jpg', 'https://images.craigslist.org/00y0y_3WHDrYlJhz0z_0CI0t3_600x450.jpg', 'https://images.craigslist.org/00w0w_7egxMeEtOhUz_0CI0t3_600x450.jpg', 'https://images.craigslist.org/00v0v_2sDi18PsIvRz_0CI0t3_600x450.jpg']",
 "url": "https://newyork.craigslist.org/brk/apa/d/brooklyn-big-bedstuy-studio-2100/7516400598.html",
 "typology": "NA",
 "GEOID": "36047027500",
 "poverty": "nonpoor",
 "race": "black",
 "white": 22.3,
 "black": 69.1,
 "asian": 7.8,
 "latinx": 9.0,
 "below25k": 13.9,
 "median_income": 86731.0,
 "college": 42.5,
 "foreignborn": 19.4,
 "renteroccupied": 68.1,
 "last10yrs": 1.0,
 "vacancy": 6.3,
 "white_old": 13.4,
 "black_old": 78.6,
 "asian_old": 4.8,
 "latinx_old": 8.1,
 "below25k_old": 11.5,
 "median_income_old": 63020.02,
 "college_old": 33.6,
 "foreignborn_old": 25.0,
 "renteroccupied_old": 60.9,
 "last10yrs_old": 0.0,
 "vacancy_old": 19.9,
 "professional": 78.5,
 "professional_old": 58.5,
 "travel_time": 43.1,
 "travel_time_old": 43.4,
 "new_residents": 35.6,
 "new_residents_old": 34.2,
 "non_english": 20.2,
 "non_english_old": 17.2,
 "avg_rent": 1749.0,
 "avg_rent_old": 1372.07
}