{
 "post_id": "7496601217",
 "title": "Gibraltar Upper Loft - Water View of Lake Erie",
 "price": "1200",
 "neighborhood": "Gibraltar, Michigan",
 "map_address": "NA",
 "street_address": "NA",
 "latitude": "42.089152",
 "longitude": "-83.186674",
 "data_accuracy": "5",
 "posted": "2022-06-14 18:01",
 "updated": "2022-07-13 12:10",
 "repost_dates": "[]",
 "available": "2022-06-15",
 "housing_type": "loft",
 "bedrooms": "1",
 "bathrooms": "1.0",
 "laundry": "w/d in unit",
 "parking": "off-street parking",
 "sqft": "880",
 "flooring": "NA",
 "rent_period": "monthly",
 "app_fee": "NA",
 "broker_fee": "NA",
 "cats_ok": "NA",
 "dogs_ok": "NA",
 "no_smoking": "True",
 "furnished": "NA",
 "wheelchair_access": "NA",
 "AC": "True",
 "EV_charging": "NA",
 "posting_body": "['Upper Loft Completely Remodeled & Ultra Modern.', 'Includes all new appliances which include, washer', '& dryer, stove, refrigerator & garbage disposal.', 'Central air, Kitchen has marble top counters.', 'Firepit and lawn chairs in common area on shorefront.', 'This is a shared property with upper and lower units.', 'All utilities are included, A/C, WIFI, heat, water & electric.', 'This upper loft is move in ready - message us today.', 'Perfect location for a couple to enjoy Lakefront comfort.', 'If you wait to long it will be gone before you know it.', '1st Month + Security Deposit required for move in!']",
 "images": "['https://images.craigslist.org/00F0F_2LrdSylirtTz_0CI0lP_600x450.jpg', 'https://images.craigslist.org/00s0s_bjclSbd8vR2z_0CI0n9_600x450.jpg', 'https://images.craigslist.org/00E0E_eTTtEpBkvNYz_0CI0t2_600x450.jpg', 'https://images.craigslist.org/00G0G_2Oh0Ps9J87Qz_0CI0t2_600x450.jpg', 'https://images.craigslist.org/00D0D_gqvyrXZfWthz_0CI0t2_600x450.jpg', 'https://images.craigslist.org/00a0a_3OlJplFmGN3z_0CI0t2_600x450.jpg', 'https://images.craigslist.org/00k0k_9i8eNjtQlfaz_0CI0t2_600x450.jpg', 'https://images.craigslist.org/01414_4Qw0pnu4tXIz_0CI0t2_600x450.jpg', 'https://images.craigslist.org/00s0s_j6eH1ABYkUWz_0CI0t2_600x450.jpg']",
 "url": "https://detroit.craigslist.org/wyn/apa/d/rockwood-gibraltar-upper-loft-water/7496601217.html",
 "typology": "NA",
 "GEOID": "26163597000",
 "poverty": "nonpoor",
 "race": "white",
 "white": 97.6,
 "black": 2.5,
 "asian": 0.5,
 "latinx": 7.9,
 "below25k": 4.4,
 "median_income": 74919.0,
 "college": 19.1,
 "foreignborn": 3.8,
 "renteroccupied": 18.4,
 "last10yrs": 0.3,
 "vacancy": 8.9,
 "white_old": 95.3,
 "black_old": 0.6,
 "asian_old": 0.2,
 "latinx_old": 4.8,
 "below25k_old": 2.8,
 "median_income_old": 71697.5,
 "college_old": 18.7,
 "foreignborn_old": 3.6,
 "renteroccupied_old": 18.7,
 "last10yrs_old": 12.9,
 "vacancy_old": 15.7,
 "professional": 48.5,
 "professional_old": 55.3,
 "travel_time": 29.4,
 "travel_time_old": 30.5,
 "new_residents": 28.6,
 "new_residents_old": 26.9,
 "non_english": 2.8,
 "non_english_old": 6.7,
 "avg_rent": 1007.0,
 "avg_rent_old": 929.39
}