{
 "post_id": 7509749213,
 "title": "6 Weeks Free!! Gorgeous Modern Uptown 1 Bed! Luxury Finishes",
 "price": 2393,
 "neighborhood": "Uptown * Capitol Hill, Downtown Denver, Lodo, City Park",
 "map_address": "NA",
 "street_address": "NA",
 "latitude": 39.7327,
 "longitude": -104.9717,
 "data_accuracy": 22,
 "posted": "2022-07-16 18:48",
 "updated": "2022-07-30 21:18",
 "repost_dates": [],
 "available": "2022-07-17",
 "housing_type": "apartment",
 "bedrooms": 1,
 "bathrooms": 1.0,
 "laundry": "w/d in unit",
 "parking": "attached garage",
 "sqft": 776,
 "flooring": "NA",
 "rent_period": "monthly",
 "app_fee": "NA",
 "broker_fee": "NA",
 "cats_ok": true,
 "dogs_ok": true,
 "no_smoking": true,
 "furnished": "NA",
 "wheelchair_access": "NA",
 "AC": true,
 "EV_charging": "NA",
 "posting_body": [
  "SPECIAL 6 WEEKS FREE!!",
  "~ New ProRated Rent = $2393 Monthly / 13 Months.",
  "Originally $2705 /month",
  "Call or Text Blake to set up tour for Fast Personal Showings or Virtual Showings",
  "Living in one of Denver\u2019s most desired neighborhoods and connected to a constant source of new and exciting experiences!",
  "Here, you will discover that complete and balanced lifestyle you\u2019ve always desired!",
  "Archive Lounge + Aperitif Retreat",
  "Pet Wash + Grooming Station",
  "Bike, Ski + Snowboard Maintenance Shop",
  "Fitness + Wellness Center with Yoga",
  "Hardwood-Style Plank Flooring Throughout",
  "Defined Entryway with Custom Built-In Bench Seating + Storage*",
  "Luxury Bathrooms with Walk-In Stone + Glass Showers*",
  "Large Walk-In Closets + Built-In Shelving*",
  "Designer Kitchens with Quartz Countertops, Euro-Style Cabinets + Open Shelving",
  "Gas-Range + GE Stainless Steel Appliances",
  "Matte Black Moen(R) Align Fixtures",
  "GE Front-Loading Washer + Dryer",
  "Call or Text Blake to set up tour for Fast Personal Showings or Virtual Showings",
  "*Restrictions Apply.",
  "Pricing, availability and lease terms subject to change anytime!"
 ],
 "images": [
  "https://images.craigslist.org/00Q0Q_aEhFtxJx0Gtz_09G07g_600x450.jpg",
  "https://images.craigslist.org/00x0x_etuKqlWIDqKz_09G07g_600x450.jpg",
  "https://images.craigslist.org/00A0A_dlMFDM8mxdIz_09G07g_600x450.jpg",
  "https://images.craigslist.org/01313_lXfHj3JusgCz_09G07g_600x450.jpg",
  "https://images.craigslist.org/00p0p_8KxqxG123Glz_09G07g_600x450.jpg",
  "https://images.craigslist.org/00o0o_2IY96zL8G0Hz_09G07g_600x450.jpg",
  "https://images.craigslist.org/00A0A_23zSLBFFPK1z_09G07g_600x450.jpg",
  "https://images.craigslist.org/00d0d_1V6bcJQfGhvz_09G07g_600x450.jpg",
  "https://images.craigslist.org/00F0F_79j3JOvbBXIz_09G07g_600x450.jpg",
  "https://images.craigslist.org/00g0g_iGeR1P67RCBz_09G07g_600x450.jpg",
  "https://images.craigslist.org/00R0R_hkCwQABCKopz_09G07g_600x450.jpg",
  "https://images.craigslist.org/00e0e_39GoBtkase3z_09G07g_600x450.jpg",
  "https://images.craigslist.org/00A0A_2bwgdkkgCmhz_09G07g_600x450.jpg",
  "https://images.craigslist.org/00g0g_fAhLrmsovekz_09G07g_600x450.jpg",
  "https://images.craigslist.org/00n0n_kGCyeuYhvctz_09G07g_600x450.jpg",
  "https://images.craigslist.org/00U0U_3N3xIqiTQ5yz_09G07g_600x450.jpg",
  "https://images.craigslist.org/00v0v_bOES2PHRVIUz_09G07g_600x450.jpg",
  "https://images.craigslist.org/00W0W_LCSgFkvKOTz_09G07g_600x450.jpg",
  "https://images.craigslist.org/00909_fj7BHxI6yVzz_09G07g_600x450.jpg",
  "https://images.craigslist.org/00j0j_1OKvD5EH2UHz_09G07g_600x450.jpg",
  "https://images.craigslist.org/00o0o_8hcgYQGjHtrz_09G07g_600x450.jpg",
  "https://images.craigslist.org/00f0f_kSKD6Sm8d6mz_09G07g_600x450.jpg",
  "https://images.craigslist.org/00z0z_aO9d8wBsvqtz_09G07g_600x450.jpg",
  "https://images.craigslist.org/00Z0Z_5B7OsgCLtgkz_09G07g_600x450.jpg"
 ],
 "url": "https://denver.craigslist.org/apa/d/denver-weeks-free-gorgeous-modern/7509749213.html"
}