{
 "post_id": 7470495820,
 "title": "Check out our grade A amenities",
 "price": 2920,
 "neighborhood": "East ATX",
 "map_address": "NA",
 "street_address": "NA",
 "latitude": 30.23712,
 "longitude": -97.715321,
 "data_accuracy": 5,
 "posted": "2022-07-24 07:53",
 "updated": "2022-08-01 12:30",
 "repost_dates": [
  "2022-07-24 07:53"
 ],
 "available": "NA",
 "housing_type": "apartment",
 "bedrooms": 2,
 "bathrooms": 2.0,
 "laundry": "w/d in unit",
 "parking": "attached garage",
 "sqft": 1277,
 "flooring": "NA",
 "rent_period": "monthly",
 "app_fee": "NA",
 "broker_fee": "NA",
 "cats_ok": true,
 "dogs_ok": true,
 "no_smoking": "NA",
 "furnished": "NA",
 "wheelchair_access": "NA",
 "AC": true,
 "EV_charging": true,
 "posting_body": [
  "Text 1625C to my cell for more info!",
  "Brand-New Apartments in Austin",
  "We are an all-new community that\u2019s redefining urban luxury in the South Shore neighborhood of Austin, Texas.",
  "Our brand-new studio, one, and two bedroom apartments are designed with sophistication and class.",
  "Premium features and spacious floor plans will make you the envy of your crew while offering an everyday sanctuary from whatever the world is throwing at you.",
  "Your downtime will get a pick-me-up with the community\u2019s A-grade amenities.",
  "Take a dip in the swimming pool, sweat it out at the state-of-the-art fitness center, quiet your mind in the lush courtyard, or simply grab a latte at the social station in the resident lounge.",
  "We have all the perks of modern living and a few you never knew you were missing.",
  "Connect with us and come see what life could be."
 ],
 "images": [
  "https://images.craigslist.org/01212_vZatTfMDoCz_0hq0hq_600x450.jpg",
  "https://images.craigslist.org/00C0C_chVgZ1zrnOdz_0hq0hq_600x450.jpg",
  "https://images.craigslist.org/00x0x_4tsxFecdlVGz_0ne0t2_600x450.jpg",
  "https://images.craigslist.org/00W0W_fPuO9XC8Mozz_0ne0t2_600x450.jpg",
  "https://images.craigslist.org/00606_dO1u0hAOZI5z_0ne0t2_600x450.jpg",
  "https://images.craigslist.org/00C0C_7WoCr4HraoWz_0ne0t2_600x450.jpg",
  "https://images.craigslist.org/00P0P_hHvfeX7fFrQz_0hq0hq_600x450.jpg",
  "https://images.craigslist.org/00q0q_9wisVY8CFzTz_0hq0hq_600x450.jpg",
  "https://images.craigslist.org/01212_d2s9VXhSkmxz_05r07g_600x450.jpg"
 ],
 "url": "https://austin.craigslist.org/apa/d/austin-check-out-our-grade-amenities/7512711253.html"
}