{
 "post_id": "7515258188",
 "title": "Storage \u2714 Open kitchen \ud83d\udc4d Garage \u2714 Walk-in closets \ud83d\udc5a",
 "price": "1780",
 "neighborhood": "Round Rock",
 "map_address": "NA",
 "street_address": "NA",
 "latitude": "30.516067",
 "longitude": "-97.669737",
 "data_accuracy": "5",
 "posted": "2022-07-30 11:43",
 "updated": "2022-08-01 14:12",
 "repost_dates": "[]",
 "available": "2022-07-31",
 "housing_type": "apartment",
 "bedrooms": "2",
 "bathrooms": "2.0",
 "laundry": "w/d in unit",
 "parking": "attached garage",
 "sqft": "1150",
 "flooring": "NA",
 "rent_period": "monthly",
 "app_fee": "NA",
 "broker_fee": "NA",
 "cats_ok": "True",
 "dogs_ok": "True",
 "no_smoking": "NA",
 "furnished": "NA",
 "wheelchair_access": "NA",
 "AC": "True",
 "EV_charging": "NA",
 "posting_body": "['Community Amenities', 'Business Center', 'Clubhouse', 'Controlled Access', 'Fitness Center', 'Garage Parking', 'Gated', 'High Speed Internet Available', 'On-Site Maintenance', 'On-Site Management', '>Package Receiving', 'Pool', 'Spa', 'Sundeck', 'Apartment Amenities', 'Air Conditioning', 'Cable', 'Ceiling Fan', 'Fireplace', 'Individual Climate Control', 'Large Closets', 'Microwave', 'Patio/Balcony', 'Storage Space', 'Washer and Dryer in unit', 'Max 2 pets allowed', 'Free service.', 'No fee.', 'LREA since 2002.', ' Broken lease?', 'Bad credit but have good income?', 'Good income', 'but no check stubs?', 'Contact me.', \"Let's talk about your options.\"]",
 "images": "['https://images.craigslist.org/00q0q_baTVopOTcWLz_0hC09z_600x450.jpg', 'https://images.craigslist.org/00K0K_gOk0HwhDCTdz_0hz09y_600x450.jpg', 'https://images.craigslist.org/00f0f_2BIE0hUvkr6z_0hw09v_600x450.jpg', 'https://images.craigslist.org/00606_5U7OH4HTLrZz_0mx0f2_600x450.jpg', 'https://images.craigslist.org/00N0N_5WUAi1iGGmCz_0mB0f5_600x450.jpg', 'https://images.craigslist.org/00f0f_2pOsUQ6EaUtz_0mA0f2_600x450.jpg', 'https://images.craigslist.org/00O0O_8kGxTLVOLa4z_0my0f2_600x450.jpg', 'https://images.craigslist.org/00d0d_cmghHOowuriz_0my0eZ_600x450.jpg', 'https://images.craigslist.org/00j0j_aRB0OMDAAvpz_0hE09w_600x450.jpg', 'https://images.craigslist.org/00B0B_3HhTo6VU5wGz_0mA0f3_600x450.jpg', 'https://images.craigslist.org/00808_6f0L6Yh6Zamz_0by07U_600x450.jpg']",
 "url": "https://austin.craigslist.org/apa/d/round-rock-storage-open-kitchen-garage/7515258188.html",
 "typology": "NA",
 "GEOID": "48491021508",
 "poverty": "NA",
 "race": "NA",
 "white": "NA",
 "black": "NA",
 "asian": "NA",
 "latinx": "NA",
 "below25k": "NA",
 "median_income": "NA",
 "college": "NA",
 "foreignborn": "NA",
 "renteroccupied": "NA",
 "last10yrs": "NA",
 "vacancy": "NA",
 "white_old": "NA",
 "black_old": "NA",
 "asian_old": "NA",
 "latinx_old": "NA",
 "below25k_old": "NA",
 "median_income_old": "NA",
 "college_old": "NA",
 "foreignborn_old": "NA",
 "renteroccupied_old": "NA",
 "last10yrs_old": "NA",
 "vacancy_old": "NA",
 "professional": "NA",
 "professional_old": "NA",
 "travel_time": "NA",
 "travel_time_old": "NA",
 "new_residents": "NA",
 "new_residents_old": "NA",
 "non_english": "NA",
 "non_english_old": "NA",
 "avg_rent": "NA",
 "avg_rent_old": "NA"
}