{
 "post_id": "6839705849",
 "title": "Charming OLD TOWN loft with sundeck, doorman, gym, CTA for Aug 18th!",
 "price": "1840",
 "neighborhood": "Old Town",
 "map_address": "Schiller near Wells",
 "street_address": "Schiller ",
 "latitude": "41.907832",
 "longitude": "-87.634653",
 "data_accuracy": "15",
 "posted": "2022-06-17 10:37",
 "updated": "2022-06-24 11:11",
 "repost_dates": "['2022-06-17 10:37']",
 "available": "2022-08-18",
 "housing_type": "apartment",
 "bedrooms": "0",
 "bathrooms": "1.0",
 "laundry": "laundry in bldg",
 "parking": "attached garage",
 "sqft": "640",
 "flooring": "NA",
 "rent_period": "monthly",
 "app_fee": "NA",
 "broker_fee": "NA",
 "cats_ok": "True",
 "dogs_ok": "NA",
 "no_smoking": "True",
 "furnished": "NA",
 "wheelchair_access": "NA",
 "AC": "NA",
 "EV_charging": "NA",
 "posting_body": "['Charming Old Town loft with walk-in closet, white cabinetry, and good storage.', 'Unit is carpeted.', 'Steps to everything, including grocery stores, shops, restaurants, bars and CTA Red and Brown lines.', 'Utilities are estimated to run around $125 based on usage.', 'Call or text Jessica at 773.419.5391!', 'Downtown Apartment Company', 'APARTMENT AMENITIES:', 'Modern & urban loft in prime Old Town location', 'Spacious floorplan', 'High ceilings with exposed wood beams and exposed brick', 'Open kitchen concept with large island', 'Gas-range', 'Large walk-in closet and other great storage', 'Great location.', 'Steps to everything Old Town has to offer', 'BUIDLING AMENITIES:', '24-hour Fitness Center', 'Package Receiving', 'On-site Laundry Center', 'Concierge Service', '5 Minutes from the Red, Brown and Purple El Lines', 'Beautifully Landscaped Courtyard', 'Business Center and Conference Room with Computers and WiFi', 'On-Site Recycling Center', 'Resident Lounge with Billiards Table and Shuffleboard', 'Sundeck with Hot Tub, Sunbathing Area and Grilling Stations', 'Call or text Jessica Odehnal at 773.419.5391!', 'Downtown Apartment Company']",
 "images": "['https://images.craigslist.org/00J0J_lo2PpLs1i1Uz_0CI0pO_600x450.jpg', 'https://images.craigslist.org/00k0k_f0INlDJDUSYz_0CI0pN_600x450.jpg', 'https://images.craigslist.org/00G0G_6GUXH6wNFE9z_0CI0pO_600x450.jpg', 'https://images.craigslist.org/00n0n_55aGDkVfBbcz_0CI0pP_600x450.jpg', 'https://images.craigslist.org/00t0t_fvEOB3J0YbPz_0CI0pQ_600x450.jpg', 'https://images.craigslist.org/00M0M_klcqtvZrvJ6z_0CI0pO_600x450.jpg', 'https://images.craigslist.org/00a0a_87LIp24rOOZz_0CI0pO_600x450.jpg', 'https://images.craigslist.org/00m0m_PKKqhZPL2cz_0CI0pO_600x450.jpg', 'https://images.craigslist.org/00U0U_hGJcO46NVBnz_0CI0pO_600x450.jpg', 'https://images.craigslist.org/01414_cdvaLHpKrSyz_0CI0pO_600x450.jpg', 'https://images.craigslist.org/00H0H_3qwjzVUNq44z_0CI0pO_600x450.jpg', 'https://images.craigslist.org/00O0O_PMlUVMmbwPz_0ak07K_600x450.jpg']",
 "url": "https://chicago.craigslist.org/chc/apa/d/chicago-charming-old-town-loft-with/7497693011.html",
 "typology": "Stable/Advanced Exclusive",
 "GEOID": "17031080300",
 "poverty": "nonpoor",
 "race": "white",
 "white": 84.5,
 "black": 1.0,
 "asian": 14.0,
 "latinx": 3.5,
 "below25k": 1.4,
 "median_income": 141439.0,
 "college": 90.0,
 "foreignborn": 12.9,
 "renteroccupied": 50.4,
 "last10yrs": 10.399999999999999,
 "vacancy": 8.7,
 "white_old": 84.7,
 "black_old": 9.0,
 "asian_old": 7.3,
 "latinx_old": 5.6,
 "below25k_old": 3.7,
 "median_income_old": 106133.72,
 "college_old": 79.8,
 "foreignborn_old": 12.7,
 "renteroccupied_old": 41.2,
 "last10yrs_old": 23.7,
 "vacancy_old": 7.7,
 "professional": 95.5,
 "professional_old": 92.30000000000001,
 "travel_time": 29.7,
 "travel_time_old": 28.7,
 "new_residents": 55.7,
 "new_residents_old": 49.8,
 "non_english": 9.2,
 "non_english_old": 16.0,
 "avg_rent": 2158.0,
 "avg_rent_old": 1641.01
}