{
 "post_id": "7516285113",
 "title": "1 Bedroom Los Feliz *\u2606* Wood Floors, Beautiful Kitchen",
 "price": "3495",
 "neighborhood": "Los Feliz - Griffith Park",
 "map_address": "4407 Ambrose Avenue near Hillhurst Ave",
 "street_address": "4407 Ambrose Avenue ",
 "latitude": "34.110152",
 "longitude": "-118.285654",
 "data_accuracy": "5",
 "posted": "2022-08-02 00:12",
 "updated": "NA",
 "repost_dates": "[]",
 "available": "2022-08-02",
 "housing_type": "apartment",
 "bedrooms": "1",
 "bathrooms": "1.0",
 "laundry": "laundry in bldg",
 "parking": "attached garage",
 "sqft": "NA",
 "flooring": "NA",
 "rent_period": "monthly",
 "app_fee": "NA",
 "broker_fee": "NA",
 "cats_ok": "True",
 "dogs_ok": "True",
 "no_smoking": "True",
 "furnished": "NA",
 "wheelchair_access": "NA",
 "AC": "True",
 "EV_charging": "NA",
 "posting_body": "['Located in Los Feliz near Griffith Park', '4407 Ambrose Avenue Los Angeles CA 90027', 'show contact info', 'Full Remodel with Modern Finishes', '\u00b7 1 Bedroom \u2013 1 Bathroom', '\u00b7 Assigned Parking Spaces', '\u00b7 $3495 / $2000 deposit / 102', 'Beautiful Designer Kitchen', '\u00b7 Quartz Countertops', '\u00b7 Kitchen Tiled Backsplash', '\u00b7 Deep Stainless-Steel Farmhouse Sink', '\u00b7 High-End Stainless-Steel Appliances', '\u00b7 Stove, Microwave, Dishwasher, Refrigerator', 'Interior Amenities', '\u00b7 Large Renovated Units', '\u00b7 Beautiful Flooring', '\u00b7 Recessed Lighting', '\u00b7 Central AC and Heating', '\u00b7 Dual Pane Windows', '\u00b7 Lots of Closet Space', '\u00b7 Custom Blinds', '\u00b7 Beautiful Fixtures Throughout', 'Community', '\u00b7 Gorgeous Landscaping', '\u00b7 Building Intercom Entry System', '\u00b7 Gated Subterranean Parking', '\u00b7 Washers & Dryers On-Site', '\u00b7 Professional On-Site Management', 'Pet Friendly Community', '\u00b7 Pets allowed: Dogs, Cats', '\u00b7 Pet restrictions: Aggressive breeds', '\u00b7 Weight limit: 25 lbs.', '\u00b7 Pet limit: 2 pets maximum', '\u00b7 Pet Deposit Required', '\u00b7 Cats \u2013 $500 deposit', '\u00b7 Dogs \u2013 $1000 deposit', 'Lease Terms', '\u00b7 12 Month Lease', '\u00b7 $60 Credit Check', 'Contact Us', 'Viewing or Leasing Information', 'Kristen', 'show contact info', 'Nearby: Silver Lake', 'Griffith Park Atwater Village', 'Thai Town Little Armenia', 'East Hollywood Silverlake', 'Echo Park Glendale', 'Hillhurst Vermont', 'Commonwealth']",
 "images": "['https://images.craigslist.org/00K0K_fRi33QgjmDtz_0CI0t2_600x450.jpg', 'https://images.craigslist.org/00C0C_8i715d225Vrz_0CH0t2_600x450.jpg', 'https://images.craigslist.org/00z0z_itEIoNRv5M7z_0CI0t2_600x450.jpg', 'https://images.craigslist.org/00f0f_dI7Ag7a3vYtz_0CI0t2_600x450.jpg', 'https://images.craigslist.org/00T0T_jkbgmB9Dk5Dz_0CI0t2_600x450.jpg', 'https://images.craigslist.org/00R0R_c5xqGNbtdFzz_0CI0t2_600x450.jpg', 'https://images.craigslist.org/00U0U_6ot3uKsOzGez_0CI0t2_600x450.jpg', 'https://images.craigslist.org/00707_SDtnJExdc7z_0CI0t2_600x450.jpg', 'https://images.craigslist.org/01111_bcZ62X2jcypz_0CI0t2_600x450.jpg', 'https://images.craigslist.org/01313_cMeO3QzYnocz_0CI0t2_600x450.jpg', 'https://images.craigslist.org/00E0E_lqa6XBC08mXz_0CI0t2_600x450.jpg', 'https://images.craigslist.org/00O0O_Cw0rUVDeHwz_0uY0ne_600x450.jpg']",
 "url": "https://losangeles.craigslist.org/lac/apa/d/los-angeles-bedroom-los-feliz-wood/7516285113.html",
 "typology": "Stable Moderate/Mixed Income",
 "GEOID": "6037189102",
 "poverty": "NA",
 "race": "NA",
 "white": "NA",
 "black": "NA",
 "asian": "NA",
 "latinx": "NA",
 "below25k": "NA",
 "median_income": "NA",
 "college": "NA",
 "foreignborn": "NA",
 "renteroccupied": "NA",
 "last10yrs": "NA",
 "vacancy": "NA",
 "white_old": "NA",
 "black_old": "NA",
 "asian_old": "NA",
 "latinx_old": "NA",
 "below25k_old": "NA",
 "median_income_old": "NA",
 "college_old": "NA",
 "foreignborn_old": "NA",
 "renteroccupied_old": "NA",
 "last10yrs_old": "NA",
 "vacancy_old": "NA",
 "professional": "NA",
 "professional_old": "NA",
 "travel_time": "NA",
 "travel_time_old": "NA",
 "new_residents": "NA",
 "new_residents_old": "NA",
 "non_english": "NA",
 "non_english_old": "NA",
 "avg_rent": "NA",
 "avg_rent_old": "NA"
}