{
 "post_id": 7499231973,
 "title": "Location! Formal Dining Room! Deco Fireplace! Small Dog Ok!",
 "price": 1275,
 "neighborhood": "North Center",
 "map_address": "Campbell near Pensacola",
 "street_address": "Campbell ",
 "latitude": 41.960431,
 "longitude": -87.691856,
 "data_accuracy": 15,
 "posted": "2022-06-21 07:55",
 "updated": "NA",
 "available": "NA",
 "housing_type": "apartment",
 "bedrooms": 1,
 "bathrooms": 1.0,
 "laundry": "laundry on site",
 "parking": "street parking",
 "sqft": "NA",
 "flooring": "NA",
 "rent_period": "monthly",
 "app_fee": "NA",
 "broker_fee": "NA",
 "cats_ok": true,
 "dogs_ok": true,
 "no_smoking": "NA",
 "furnished": "NA",
 "wheelchair_access": "NA",
 "AC": "NA",
 "EV_charging": "NA",
 "posting_body": "  QR Code Link to This Post   Check Out This North Center 1bd Ready Now!  Large Living Room, Formal Dining Room, Major Closet Space, & Large Bedroom!  Hardwood Floors, Deco Fireplace, & Ceiling Fans W/Lighting!   Kitchen W/Dishwasher!   Secure Entry, Bike Storage, & Onsite Laundry!  Small Dog Under 35lbs Ok No Aggressive Breeds!  Email Or Txt  Joseph Perez Landstar Realty Group, Inc.  630-709-1606 ",
 "images": [
  "https://images.craigslist.org/00B0B_cfm31p8QtjEz_0lM0t2_600x450.jpg",
  "https://images.craigslist.org/00u0u_5sXn7IV87djz_0lM0t2_600x450.jpg",
  "https://images.craigslist.org/00Q0Q_9WsoK3kK7Hvz_0lM0t2_600x450.jpg",
  "https://images.craigslist.org/00R0R_byM7gP8DnGFz_0lM0t2_600x450.jpg",
  "https://images.craigslist.org/00T0T_lL8jhkoqSMBz_0lM0t2_600x450.jpg",
  "https://images.craigslist.org/00b0b_gg0NSPTWfXwz_0lM0t2_600x450.jpg",
  "https://images.craigslist.org/00r0r_en7JECp9VyCz_0lM0t2_600x450.jpg",
  "https://images.craigslist.org/00s0s_b3qZvirqALuz_0lM0t2_600x450.jpg",
  "https://images.craigslist.org/00l0l_9ROii8mwiUqz_07N08l_600x450.jpg"
 ],
 "url": "https://chicago.craigslist.org/chc/apa/d/chicago-location-formal-dining-room/7499231973.html"
}