{
 "post_id": 7505835864,
 "title": "Harvard Square Loft: 2 full bath, Chefs Kitchen, Garage, Yard",
 "price": 5800,
 "neighborhood": "Harvard Square Agassiz",
 "map_address": "36 Irving St near Kirkland St",
 "street_address": "36 Irving St ",
 "latitude": 42.37612,
 "longitude": -71.110847,
 "data_accuracy": 10,
 "posted": "2022-07-07 11:43",
 "updated": "2022-07-26 12:41",
 "repost_dates": [],
 "available": "2022-07-26",
 "housing_type": "townhouse",
 "bedrooms": 3,
 "bathrooms": 2.0,
 "laundry": "w/d in unit",
 "parking": "attached garage",
 "sqft": 1300,
 "flooring": "NA",
 "rent_period": "monthly",
 "app_fee": "NA",
 "broker_fee": "NA",
 "cats_ok": "NA",
 "dogs_ok": "NA",
 "no_smoking": true,
 "furnished": "NA",
 "wheelchair_access": "NA",
 "AC": true,
 "EV_charging": "NA",
 "posting_body": [
  "No Fee Harvard Sq Loft: 3BD/2BA, Chefs Kit, Garage plus off street parking, Yard, Central AC and Fireplace.",
  " Beautiful Loft, Bell and Fandetti post and beam townhouse located on Professor's Row.",
  "This house features: - Heated garage plus an additional off-street parking place providing 2 car private parking.",
  "- Cathedral ceiling w built-Ins, large windows, and a wood-burning stove/fireplace.",
  "-The main level includes a spacious open concept living/dining/kitchen area-which is perfect for entertaining.",
  "-",
  "The Chef's kitchen is fully equipped w/high-end Stainless Steel appliances including a 36\" Viking stove and hood and granite countertops.",
  "- The master BR has windows which look out over the canopy of a large maple in the backyard and you can see the moon and stars at night.",
  "- Other features include a study, 2 full bathrooms, in unit washer/dryer, central A/C, new furnace, a fenced private yard with deck and a lot of wood, natural light and hardwood floors throughout."
 ],
 "images": [
  "https://images.craigslist.org/00l0l_aSM3oCRC2R3z_0gw0co_600x450.jpg",
  "https://images.craigslist.org/00R0R_7woY68XAqxGz_0gw0co_600x450.jpg",
  "https://images.craigslist.org/00W0W_gvJMzEcQstqz_0gw0co_600x450.jpg",
  "https://images.craigslist.org/00s0s_8EVQ3p1oLQMz_0gw0co_600x450.jpg",
  "https://images.craigslist.org/00303_6csnMgd9sEsz_08g0co_600x450.jpg",
  "https://images.craigslist.org/01414_ci8KEXPKuJFz_0gw0co_600x450.jpg",
  "https://images.craigslist.org/00n0n_8vSRxOTaQstz_0gw0b1_600x450.jpg",
  "https://images.craigslist.org/00s0s_848XIn9HjrMz_0gw0co_600x450.jpg",
  "https://images.craigslist.org/00101_kSc8xSzNdD4z_09i0co_600x450.jpg",
  "https://images.craigslist.org/00K0K_bVvW1f9uPFz_09i0co_600x450.jpg",
  "https://images.craigslist.org/00x0x_gVmYOVnHdf4z_0gw0co_600x450.jpg",
  "https://images.craigslist.org/00505_3qzYzIv2a08z_0gw0co_600x450.jpg",
  "https://images.craigslist.org/01111_2GvFNPEHT06z_0ak07K_600x450.jpg",
  "https://images.craigslist.org/00T0T_gFEPM4VM2AQz_0gU0pz_600x450.jpg",
  "https://images.craigslist.org/00g0g_7KYS4kco40mz_0hd0gF_600x450.jpg",
  "https://images.craigslist.org/01212_jjt3aV0b3Cuz_0j10j1_600x450.jpg",
  "https://images.craigslist.org/00y0y_5faAuRDEOJcz_0id0oi_600x450.jpg",
  "https://images.craigslist.org/00000_7b7Xlmw32muz_0g00aK_600x450.jpg",
  "https://images.craigslist.org/00G0G_6xYqldhDOmdz_0rq0fu_600x450.jpg",
  "https://images.craigslist.org/00s0s_ewIVwoSAsjlz_03j03N_600x450.jpg"
 ],
 "url": "https://boston.craigslist.org/gbs/apa/d/cambridge-harvard-square-loft-full-bath/7505835864.html"
}