{
 "post_id": 7516486865,
 "title": "Pet-Friendly, Dishwasher, BBQ Area, Clubhouse",
 "price": 1815,
 "neighborhood": "Port Orchard",
 "map_address": "1800 Sidney Ave near Sidney and Poplar",
 "street_address": "1800 Sidney Ave ",
 "latitude": 47.521681,
 "longitude": -122.644504,
 "data_accuracy": 10,
 "posted": "2022-08-02 11:46",
 "updated": "NA",
 "repost_dates": [],
 "available": "NA",
 "housing_type": "apartment",
 "bedrooms": 2,
 "bathrooms": 2.0,
 "laundry": "w/d in unit",
 "parking": "carport",
 "sqft": 982,
 "flooring": "NA",
 "rent_period": "monthly",
 "app_fee": "NA",
 "broker_fee": "NA",
 "cats_ok": true,
 "dogs_ok": true,
 "no_smoking": "NA",
 "furnished": "NA",
 "wheelchair_access": true,
 "AC": true,
 "EV_charging": "NA",
 "posting_body": [
  "Atlas",
  "1800 Sidney Ave , Port Orchard, WA, 98366",
  "Want more info?",
  "See the link below:",
  "<URL>",
  "Call Now:",
  "show contact info",
  "x 73",
  "OR Text",
  "73",
  "to",
  "show contact info",
  "to text our leasing team.",
  "DISCOVER YOUR OWN SECRET HIDEAWAY",
  "This is a 2 Bedroom, 2 Bath, approximately 982 Sq.",
  "Ft.",
  "Located in the sweet spot between nature and city, Atlas Apartments offers the very best of the Pacific Northwest in a three-story, garden-style community.",
  "With ferry access to Seattle, luxury amenities, and the majestic Olympic Mountains framing the horizon, the life you\u2019ve always dreamed of is now within reach!",
  "Features",
  "- Walk-in Closets*",
  "- Carpeting",
  "- Trash Compactor",
  "- Ceiling Fan*",
  "- Hardwood Floors",
  "- Wheelchair Accessible (Rooms)",
  "- Full Size Washer/Dryer in Unit",
  "- Renovated Finishes",
  "- Handrails",
  "- Storage Units",
  "- Dishwasher",
  "- Brick Fireplaces*",
  "- Spacious Floor Plans",
  "- Disposal",
  "*In select untis",
  "Community Amenities",
  "- Outdoor Pool and Spa",
  "- Outdoor Basketball Court",
  "- Patio Or Balcony",
  "- Sundeck",
  "- Pet-Friendly",
  "- Quiet Surroundings, views of Olympic Mountains",
  "- Business Center",
  "- Close to Freeways",
  "- Covered Parking",
  "- Free WiFi In Common Areas",
  "- Clubhouse",
  "- Playground",
  "- Package Concierge Service",
  "- Parking Garages",
  "- Indoor Racquetball Court",
  "- BBQ Area",
  "- Extra Storage",
  "- Efficient Appliances",
  "- Faux stone countertops",
  "- Conveniently Located to Navy Bases and Hospital",
  "- Surrounding Wooded Areas",
  "- Views of Olympic Mountains",
  "- Public Transportation",
  "- Fitness Center",
  "Office Hours",
  "Monday-Friday:9:00AM-6:00PM",
  "Saturday:10:00AM-5:00PM",
  "dYujvlf77482"
 ],
 "images": [
  "https://images.craigslist.org/00g0g_jn4oVPpek6uz_0ak07K_600x450.jpg",
  "https://images.craigslist.org/00E0E_24ZmUrdYCXJz_0ak07K_600x450.jpg",
  "https://images.craigslist.org/00d0d_3ZLrsWfriBPz_0ak07K_600x450.jpg",
  "https://images.craigslist.org/00Q0Q_cwVIWQWwU9Ez_0ak07K_600x450.jpg",
  "https://images.craigslist.org/00D0D_97uO4ogvnRqz_0ak07K_600x450.jpg"
 ],
 "url": "https://seattle.craigslist.org/kit/apa/d/retsil-pet-friendly-dishwasher-bbq-area/7516486865.html"
}