{
 "post_id": "7516199366",
 "title": "2x1 coming soon",
 "price": "1869",
 "neighborhood": "PUYALLUP",
 "map_address": "3107 East Main Avenue",
 "street_address": "3107 East Main Avenue",
 "latitude": "47.2042",
 "longitude": "-122.2734",
 "data_accuracy": "22",
 "posted": "2022-08-01 16:46",
 "updated": "NA",
 "repost_dates": "[]",
 "available": "2022-08-06",
 "housing_type": "apartment",
 "bedrooms": "2",
 "bathrooms": "1.0",
 "laundry": "w/d in unit",
 "parking": "carport",
 "sqft": "861",
 "flooring": "NA",
 "rent_period": "monthly",
 "app_fee": "NA",
 "broker_fee": "NA",
 "cats_ok": "True",
 "dogs_ok": "True",
 "no_smoking": "NA",
 "furnished": "NA",
 "wheelchair_access": "NA",
 "AC": "NA",
 "EV_charging": "NA",
 "posting_body": "['Featuring picturesque, tree-lined river trails and lushly landscaped gardens, Riverside Park offers spacious, 1, 2, and 3 bedroom apartment homes with gourmet kitchens, private decks and full-sized washers and dryers.', 'Right on the border of Sumner and Puyallup, Riverside Park is just minutes from schools, shopping, parks and Highways 167, 512 and 410.', '*Amenities', '>Spacious, Open Floor Plan', '>Breakfast Bar', '>Mountain Views', '>Wood-burning Fireplace', '>Full-Sized Washers & Dryers', 'Choosing your home is important.', 'Choosing your neighborhood is just as important.', 'Live moments away from the quant downtown Sumner district and within minutes from the downtown Puyallup area always alive with opportunity and fun events.', 'Whether you are looking for a one, two, or three bedroom apartment, Riverside park has a floorplan to fit your needs.', 'Visit Riverside Park Apartments, take a tour with us and let us introduce you to the community.', '*SPECIALS', \"For our 2x1's we are waiving the admin and application fee upon move in!\"]",
 "images": "['https://images.craigslist.org/00H0H_bMM1iWM88wPz_0CI0lM_600x450.jpg', 'https://images.craigslist.org/00101_64uT76HbqpRz_0CI0lM_600x450.jpg', 'https://images.craigslist.org/00404_fi84Kpwvo9Zz_0CI0lM_600x450.jpg', 'https://images.craigslist.org/00A0A_4qNTSnjApfez_0CI0lM_600x450.jpg', 'https://images.craigslist.org/00a0a_kVVla6Uo2qAz_0CI0lM_600x450.jpg', 'https://images.craigslist.org/00U0U_gwwi7g9Q8Inz_0CI0lM_600x450.jpg', 'https://images.craigslist.org/00n0n_aelDJfQFmklz_0CI0lM_600x450.jpg', 'https://images.craigslist.org/00c0c_iS1xnFQgyD0z_0CI0lM_600x450.jpg', 'https://images.craigslist.org/00B0B_d0I53gopTH4z_0CI0lM_600x450.jpg', 'https://images.craigslist.org/00M0M_cRR9NsECPRHz_0CI0lM_600x450.jpg', 'https://images.craigslist.org/00P0P_94IuZPoPanxz_0CI0lM_600x450.jpg', 'https://images.craigslist.org/00A0A_46qUfJH5ZN3z_0CI0lM_600x450.jpg', 'https://images.craigslist.org/00Y0Y_einrHzNpba6z_0CI0lM_600x450.jpg', 'https://images.craigslist.org/00B0B_hjiHVG4GSxoz_0CI0n0_600x450.jpg', 'https://images.craigslist.org/00m0m_5w8ff6N109Ez_0uY0hq_600x450.jpg']",
 "url": "https://seattle.craigslist.org/see/apa/d/puyallup-2x1-coming-soon/7516199366.html",
 "typology": "Ongoing Displacement",
 "GEOID": "53053940010",
 "poverty": "nonpoor",
 "race": "white",
 "white": 79.6,
 "black": 12.0,
 "asian": 7.6,
 "latinx": 9.7,
 "below25k": 0.5,
 "median_income": 68750.0,
 "college": 19.2,
 "foreignborn": 10.9,
 "renteroccupied": 43.1,
 "last10yrs": 10.5,
 "vacancy": 4.1,
 "white_old": 94.9,
 "black_old": 0.6,
 "asian_old": 0.7,
 "latinx_old": 7.6,
 "below25k_old": 9.5,
 "median_income_old": 47842.759999999995,
 "college_old": 12.8,
 "foreignborn_old": 4.7,
 "renteroccupied_old": 41.2,
 "last10yrs_old": 10.5,
 "vacancy_old": 9.8,
 "professional": 51.4,
 "professional_old": 48.0,
 "travel_time": 30.8,
 "travel_time_old": 25.6,
 "new_residents": 50.0,
 "new_residents_old": 37.8,
 "non_english": 13.7,
 "non_english_old": 6.3,
 "avg_rent": 1424.0,
 "avg_rent_old": 1238.79
}