{
 "post_id": "7516408244",
 "title": "Covered Lot, Outdoor Pool, Gym, Washer & Dryer In Unit",
 "price": "1819",
 "neighborhood": "NA",
 "map_address": "9210 South Hosmer Street",
 "street_address": "9210 South Hosmer Street",
 "latitude": "47.1464",
 "longitude": "-122.4572",
 "data_accuracy": "5",
 "posted": "2022-08-02 09:16",
 "updated": "NA",
 "repost_dates": "[]",
 "available": "2022-08-02",
 "housing_type": "apartment",
 "bedrooms": "2",
 "bathrooms": "2.0",
 "laundry": "w/d in unit",
 "parking": "carport",
 "sqft": "950",
 "flooring": "NA",
 "rent_period": "daily",
 "app_fee": "NA",
 "broker_fee": "NA",
 "cats_ok": "True",
 "dogs_ok": "True",
 "no_smoking": "True",
 "furnished": "NA",
 "wheelchair_access": "NA",
 "AC": "NA",
 "EV_charging": "NA",
 "posting_body": "['9210 South Hosmer Street, Tacoma, WA 98444', 'Notch 8 Apartments is located in Tacoma, Washington.', 'With close proximity to shopping, dining, and entertainment options, you have everything within arms reach.', 'Public transportation options are located nearby, along with Joint Base Lewis McChord, and access to I-5, and Hwy 512, making any commute a breeze.', 'Apartment Features:', 'Window Coverings', 'Washer & Dryer In Unit', 'Cable or Satellite', 'Garbage Disposal', 'Ceiling Fan', 'Patio or Balcony', 'Community Features:', 'Fitness Center', 'Zero Deposit Community', 'Public Transportation Nearby', 'Covered Lot', 'Nearby Freeway Access', 'Outdoor Swimming Pool', 'Call:', 'show contact info', 'For more information, visit us at: <URL>', '*Pricing and availability are subject to change daily.', 'Photos may not be of the exact advertised unit.', 'Please contact us today for the most up to date information!']",
 "images": "['https://images.craigslist.org/00707_kJJKz6PIjx3z_0gw0b2_600x450.jpg', 'https://images.craigslist.org/00q0q_6nLQUJz9aBsz_0gw0b2_600x450.jpg', 'https://images.craigslist.org/01515_6utNd11Vw9rz_0gw0b2_600x450.jpg', 'https://images.craigslist.org/00w0w_7xEunqguudVz_0go0an_600x450.jpg', 'https://images.craigslist.org/00g0g_kiAzjLlUViBz_0gm09Z_600x450.jpg', 'https://images.craigslist.org/00x0x_gurlOwWNPL1z_0bO0aY_600x450.jpg', 'https://images.craigslist.org/00x0x_38vP8EciAhTz_0gq0a7_600x450.jpg', 'https://images.craigslist.org/00f0f_7GV7QxFsUSCz_0gw0b2_600x450.jpg', 'https://images.craigslist.org/00U0U_fFnXcH7Dg8Vz_09i0fl_600x450.jpg']",
 "url": "https://seattle.craigslist.org/est/apa/d/tacoma-covered-lot-outdoor-pool-gym/7516408244.html",
 "typology": "High Student Population",
 "GEOID": "53053071504",
 "poverty": "nonpoor",
 "race": "white",
 "white": 66.5,
 "black": 20.6,
 "asian": 12.9,
 "latinx": 10.1,
 "below25k": 22.3,
 "median_income": 48583.0,
 "college": 17.3,
 "foreignborn": 12.2,
 "renteroccupied": 55.6,
 "last10yrs": 9.4,
 "vacancy": 4.7,
 "white_old": 84.5,
 "black_old": 10.6,
 "asian_old": 3.3,
 "latinx_old": 9.7,
 "below25k_old": 18.7,
 "median_income_old": 42974.47,
 "college_old": 17.6,
 "foreignborn_old": 6.0,
 "renteroccupied_old": 62.7,
 "last10yrs_old": 0.0,
 "vacancy_old": 6.4,
 "professional": 49.1,
 "professional_old": 48.3,
 "travel_time": 23.3,
 "travel_time_old": 20.7,
 "new_residents": 48.6,
 "new_residents_old": 37.8,
 "non_english": 19.3,
 "non_english_old": 10.7,
 "avg_rent": 1091.0,
 "avg_rent_old": 881.79
}