{
 "post_id": "7508074229",
 "title": "1 bedroom apartment, only 500 feet to Surfers Beach",
 "price": "2185",
 "neighborhood": "half moon bay",
 "map_address": "518 Avenue Alhambra",
 "street_address": "518 Avenue Alhambra",
 "latitude": "37.502781",
 "longitude": "-122.471294",
 "data_accuracy": "5",
 "posted": "2022-07-12 17:08",
 "updated": "2022-08-02 15:57",
 "repost_dates": "[]",
 "available": "2022-07-12",
 "housing_type": "apartment",
 "bedrooms": "1",
 "bathrooms": "1.0",
 "laundry": "laundry in bldg",
 "parking": "carport",
 "sqft": "480",
 "flooring": "NA",
 "rent_period": "monthly",
 "app_fee": "NA",
 "broker_fee": "NA",
 "cats_ok": "True",
 "dogs_ok": "True",
 "no_smoking": "True",
 "furnished": "NA",
 "wheelchair_access": "NA",
 "AC": "NA",
 "EV_charging": "NA",
 "posting_body": "['Half Moon Bay is known for its cool summer Mediterranean climate and mild winters.', 'This one-bedroom is ideal for someone who enjoys the small-town life and ocean lifestyle.', 'New carpet.', 'Newly painted.', 'Carport parking for one vehicle.', 'Walk-in closet.', 'Laundry in the building.', 'Rent: $2,185.', 'Deposit: $2,185.', 'The lease terms are for one year.', \"All utilities are the tenant's responsibility.\", 'Pet NR fee and deposit required.', 'Must have a positive rental, credit history, job references, background check', 'Please call to schedule an appointment to view this unit.', 'Mayra - Coldwell Banker Commercial', 'show contact info']",
 "images": "['https://images.craigslist.org/00k0k_1DbmvWcYrrmz_0CI0t2_600x450.jpg', 'https://images.craigslist.org/00H0H_3A1HI6KRoj5z_0lM0t2_600x450.jpg', 'https://images.craigslist.org/00V0V_dou2Y7VuYcRz_0lM0t2_600x450.jpg', 'https://images.craigslist.org/00z0z_kh6mC9CtyjGz_0lM0t2_600x450.jpg', 'https://images.craigslist.org/00F0F_j0hT5ZEEsPaz_0CI0t2_600x450.jpg', 'https://images.craigslist.org/00L0L_3qBsp5MC2kHz_0CI0t2_600x450.jpg', 'https://images.craigslist.org/00A0A_hfnAizpdosVz_0CI0t2_600x450.jpg', 'https://images.craigslist.org/00N0N_e8qHrufvQExz_0lM0t2_600x450.jpg', 'https://images.craigslist.org/00s0s_kFfDfM7ERevz_0lM0t2_600x450.jpg', 'https://images.craigslist.org/00e0e_8hQ2geq0Tf9z_0CI0t2_600x450.jpg']",
 "url": "https://sfbay.craigslist.org/pen/apa/d/el-granada-bedroom-apartment-only-500/7508074229.html",
 "typology": "Stable/Advanced Exclusive",
 "GEOID": "6081613502",
 "poverty": "NA",
 "race": "NA",
 "white": "NA",
 "black": "NA",
 "asian": "NA",
 "latinx": "NA",
 "below25k": "NA",
 "median_income": "NA",
 "college": "NA",
 "foreignborn": "NA",
 "renteroccupied": "NA",
 "last10yrs": "NA",
 "vacancy": "NA",
 "white_old": "NA",
 "black_old": "NA",
 "asian_old": "NA",
 "latinx_old": "NA",
 "below25k_old": "NA",
 "median_income_old": "NA",
 "college_old": "NA",
 "foreignborn_old": "NA",
 "renteroccupied_old": "NA",
 "last10yrs_old": "NA",
 "vacancy_old": "NA",
 "professional": "NA",
 "professional_old": "NA",
 "travel_time": "NA",
 "travel_time_old": "NA",
 "new_residents": "NA",
 "new_residents_old": "NA",
 "non_english": "NA",
 "non_english_old": "NA",
 "avg_rent": "NA",
 "avg_rent_old": "NA"
}