{
 "post_id": 7516632492,
 "title": "Studio Unit in Nob Hill ,It's available on 9/10/2022",
 "price": 2100,
 "neighborhood": "lower nob hill",
 "map_address": "pacific ave near powell st",
 "street_address": "pacific ave ",
 "latitude": 37.796493,
 "longitude": -122.410076,
 "data_accuracy": 15,
 "posted": "2022-08-02 17:24",
 "updated": "NA",
 "repost_dates": [],
 "available": "2022-09-10",
 "housing_type": "apartment",
 "bedrooms": 1,
 "bathrooms": 1.0,
 "laundry": "laundry in bldg",
 "parking": "no parking",
 "sqft": 230,
 "flooring": "NA",
 "rent_period": "monthly",
 "app_fee": "NA",
 "broker_fee": "NA",
 "cats_ok": "NA",
 "dogs_ok": "NA",
 "no_smoking": true,
 "furnished": true,
 "wheelchair_access": "NA",
 "AC": "NA",
 "EV_charging": "NA",
 "posting_body": [
  "Rent: $2100/mon, in SF /fully furnished,",
  "One month's security deposit required to sign the lease, first month's rent required to move in",
  "This special place was completely renovated and close to Chinatown, Union Square, Financial District, and Fisherman's Wharf.",
  "There's a Bus stop and Cable Cars near the corner making it easy to plan your visit.",
  "1b1b,include wifi ,water, electric, Available on Sep 10, 2022",
  "NOTE: Parking is difficult, no pets, no smoking",
  "Muni #10 and #12 stop down the street.",
  "5 minutes walking to North Beach.",
  "10 minutes walking to Fidi and Union Square.",
  "15 minutes walking to the Montgomery Bart station and SF Ferry Building.",
  "If you're interested in the room, DM me for details.",
  "Thanks!"
 ],
 "images": [
  "https://images.craigslist.org/00i0i_g6VVeTV8BVFz_0pO0jm_600x450.jpg",
  "https://images.craigslist.org/00s0s_8Z9ZzwTjcizz_0t20CI_600x450.jpg",
  "https://images.craigslist.org/00000_86058N1OBTMz_0CI0rj_600x450.jpg",
  "https://images.craigslist.org/00B0B_2nMzJ4YPkYLz_0CI0t2_600x450.jpg"
 ],
 "url": "https://sfbay.craigslist.org/sfc/apa/d/san-francisco-studio-unit-in-nob-hill/7516632492.html"
}