{
 "post_id": "6828476051",
 "title": "Section 8 1 Br 1 Ba Available Now No voucher needed  No Wait List",
 "price": "25",
 "neighborhood": "Granite Falls Mn",
 "map_address": "108 Baldwin St near Miller Ave",
 "street_address": "108 Baldwin St ",
 "latitude": "44.802306",
 "longitude": "-95.541058",
 "data_accuracy": "5",
 "posted": "2022-07-13 08:40",
 "updated": "2022-08-01 12:59",
 "repost_dates": "['2022-07-13 08:40']",
 "available": "NA",
 "housing_type": "apartment",
 "bedrooms": "1",
 "bathrooms": "1.0",
 "laundry": "laundry in bldg",
 "parking": "off-street parking",
 "sqft": "650",
 "flooring": "NA",
 "rent_period": "monthly",
 "app_fee": "NA",
 "broker_fee": "NA",
 "cats_ok": "True",
 "dogs_ok": "True",
 "no_smoking": "True",
 "furnished": "NA",
 "wheelchair_access": "NA",
 "AC": "NA",
 "EV_charging": "NA",
 "posting_body": "['BEAUTIFUL APARTMENTS ON THE MINNESOTA RIVER!', 'In Beautiful Granite Falls.', '1 Bedroom Apts', 'Contact info:', 'Terri', 'show contact info', '1Bd/1Ba Apartment', '108 Baldwin St, Granite Falls, MN 56241', '$25-$698/mo', 'KEY FEATURES', 'Sq Footage:', '650 sqft.', 'Bedrooms:', '1 Bed', 'Bathrooms:', '1 Bath', 'Parking:', '1 Off street | Guest parking', 'Lease Duration:', '1 Year (See Details Below)', 'Deposit:', '$25-$698', 'Pets Policy: Service Animals Only', 'Laundry:', 'Shared', 'Property Type:', 'Apartment', 'DESCRIPTION', 'This property sits on the beautiful Minnesota River with river views from our community room , your living room and bedroom.', 'We are a section 8 housing property so your rent is based on your income, All utilities are included.', 'If you have any questions, want to set up a tour or have an application sent to you please contact our office by responding to this ad or calling', 'show contact info', '.', 'RENTAL FEATURES', 'Living room', 'Dinning Area', 'Breakfast nook', 'Lots of Closets', 'Pantry', 'Range / Oven', 'Refrigerator', 'New Carpet', 'New Appliances', 'Fresh Paint', 'Cable Ready', 'Bright and Airy', 'New Appliances', 'Cable-ready', 'COMMUNITY FEATURES', 'Waterfront', 'Elevator', 'Controlled access', \"2 Community Rooms W/ Big Screen TV's and Cable\", 'Pool Table', 'Gazebo', 'Barbecue area', 'Playground', 'Guest parking', 'Off-street parking', 'LEASE TERMS', '1 Year lease.', 'You must have verifiable rental history for at least 1 year or have been displaced due to Covid , Rent based on your income rent can range from $25 to $698', 'If you have any questions, would like to set up a tour , or have an application mailed to you please contact our office by responding to this ad or calling', 'show contact info', '.', 'Contact info:', 'show contact info']",
 "images": "['https://images.craigslist.org/01414_ddkJxhPPMr0z_0x20oM_600x450.jpg', 'https://images.craigslist.org/00I0I_bSbCpsHNeXUz_0lM0t2_600x450.jpg', 'https://images.craigslist.org/00A0A_dMWASwV11Xqz_0t20CI_600x450.jpg', 'https://images.craigslist.org/00b0b_cN06mHe0kX1z_0t20CI_600x450.jpg', 'https://images.craigslist.org/01010_hP3rbbSpqfJz_0t20CI_600x450.jpg', 'https://images.craigslist.org/00c0c_i8W13taPTehz_0t20CI_600x450.jpg', 'https://images.craigslist.org/01212_lOxYSikCwIKz_0lM0t2_600x450.jpg', 'https://images.craigslist.org/00808_jx4zk6FcJsFz_0t20CI_600x450.jpg', 'https://images.craigslist.org/01616_brqEKU83ekFz_0t20CI_600x450.jpg', 'https://images.craigslist.org/00505_3TvtAflnVjUz_0t20CI_600x450.jpg', 'https://images.craigslist.org/00d0d_4Kky0pv0qHz_0lM0t2_600x450.jpg', 'https://images.craigslist.org/01515_25MGXGSs5rpz_0t20CI_600x450.jpg', 'https://images.craigslist.org/00a0a_7W9ozxUIfY1z_0t20CI_600x450.jpg', 'https://images.craigslist.org/00m0m_fO5ic5mY66uz_0lM0t2_600x450.jpg', 'https://images.craigslist.org/00Z0Z_hbD2ACSROIHz_0lM0t2_600x450.jpg', 'https://images.craigslist.org/00h0h_b9FCRh32Ex0z_0x20oM_600x450.jpg', 'https://images.craigslist.org/00N0N_LGIa9zrs1Uz_0lM0t2_600x450.jpg', 'https://images.craigslist.org/00D0D_7dikDgFQifTz_0lM0t2_600x450.jpg', 'https://images.craigslist.org/00505_kYE3XboCTxoz_0x20oM_600x450.jpg', 'https://images.craigslist.org/00s0s_hZYI10TmJZAz_0CI0mz_600x450.jpg', 'https://images.craigslist.org/00M0M_dB5SMCTxZx9z_0x20oM_600x450.jpg', 'https://images.craigslist.org/00S0S_7vbOOoAxfejz_0hk0kG_600x450.jpg']",
 "url": "https://minneapolis.craigslist.org/ram/apa/d/granite-falls-section-1-br-ba-available/7508202377.html",
 "typology": "NA",
 "GEOID": "27173970100",
 "poverty": "nonpoor",
 "race": "white",
 "white": 92.1,
 "black": 2.2,
 "asian": 0.5,
 "latinx": 5.2,
 "below25k": 7.8,
 "median_income": 61071.0,
 "college": 19.2,
 "foreignborn": 0.5,
 "renteroccupied": 26.2,
 "last10yrs": 1.2000000000000002,
 "vacancy": 8.5,
 "white_old": 92.3,
 "black_old": 2.9,
 "asian_old": 0.5,
 "latinx_old": 2.7,
 "below25k_old": 12.9,
 "median_income_old": 63189.0,
 "college_old": 19.7,
 "foreignborn_old": 0.4,
 "renteroccupied_old": 23.7,
 "last10yrs_old": 7.7,
 "vacancy_old": 9.9,
 "professional": 61.6,
 "professional_old": 53.599999999999994,
 "travel_time": 16.7,
 "travel_time_old": 14.5,
 "new_residents": 20.9,
 "new_residents_old": 26.1,
 "non_english": 2.2,
 "non_english_old": 2.6,
 "avg_rent": 660.0,
 "avg_rent_old": 774.6899999999999
}