{
 "post_id": "7513253869",
 "title": "BRAND-NEW 1 BR Apt Available! Apply Today Before It\u2019s Gone!",
 "price": "1532",
 "neighborhood": "Downtown Minneapolis",
 "map_address": "Nicollet Avenue near 15th Street",
 "street_address": "Nicollet Avenue ",
 "latitude": "44.968105",
 "longitude": "-93.277817",
 "data_accuracy": "15",
 "posted": "2022-07-25 13:52",
 "updated": "2022-08-01 14:55",
 "repost_dates": "[]",
 "available": "2022-08-01",
 "housing_type": "apartment",
 "bedrooms": "1",
 "bathrooms": "1.0",
 "laundry": "w/d in unit",
 "parking": "attached garage",
 "sqft": "749",
 "flooring": "NA",
 "rent_period": "monthly",
 "app_fee": "NA",
 "broker_fee": "NA",
 "cats_ok": "True",
 "dogs_ok": "True",
 "no_smoking": "True",
 "furnished": "NA",
 "wheelchair_access": "True",
 "AC": "True",
 "EV_charging": "True",
 "posting_body": "['Take a Video Tour Today', '> Check out the video walkthroughs of our community\u2019s amenities and apartment homes!', 'If you are interested in an in-person tour, feel free to call or email us at any time.', 'Please use the link in this ad to view our video tours & options to contact us directly.', 'HURRY \u2013 our new rent-restricted apartments are going fast!', 'Submit your application paperwork quickly and easily today to reserve your brand-new home!', '1500 Nicollet \u2013 A one-of-a-kind Twin Cities apartment living community!', 'We\u2019ve designed these apartment homes with you in mind and are offering smart layouts, quality materials, and luxurious amenities seldom found in this price range.', 'Enjoy the comforts of maintenance-free living along with the convenience of an outstanding location.', 'These one, two and three bedroom apartments feature open & spacious floor plans, a full-size washer & dryer, energy efficient lighting & appliances, large windows providing tons of natural sunlight, and individually controlled heating & air conditioning.', 'Make 1500 Nicollet your home today!', 'Specific layouts & square footage may vary according to specific floor plan types.', 'All finishes & appliances are the same in every home.', 'Community Amenities Include:', '- WaterSense Plumbing Fixtures', '- Individually Controlled Heating & Air-Conditioning', '- Huge Exterior Courtyard Area', '- Pet-Friendly Community', '- Modern Interior Home Design', '- Gorgeous Kitchen Cabinetry with Quartz Countertops', '- On-Site Fitness Center & Yoga Studio', 'We are a pet-friendly community.', 'Dogs & cats welcome!', 'See Respective Floor Plan Info -', 'Office Hours:', 'Monday-Friday: 11:00AM-6:00PM', 'Make the move today by giving our professional staff a call:', 'show contact info', '1500 Nicollet', '1500 Nicollet Ave.', 'South', 'Minneapolis, MN, 55403', '<URL>', '*Some Restrictions May Apply.', 'uGpxY2D4zFla']",
 "images": "['https://images.craigslist.org/00E0E_8Z0D2yxirMcz_0ak07K_600x450.jpg', 'https://images.craigslist.org/00a0a_gLhWnRTRREcz_0ak07K_600x450.jpg', 'https://images.craigslist.org/00n0n_kvq1DsSC4XHz_0ak07K_600x450.jpg', 'https://images.craigslist.org/00303_hmgewodWHtaz_0ak07K_600x450.jpg']",
 "url": "https://minneapolis.craigslist.org/hnp/apa/d/minneapolis-brand-new-br-apt-available/7513253869.html",
 "typology": "NA",
 "GEOID": "27053105204",
 "poverty": "nonpoor",
 "race": "white",
 "white": 72.1,
 "black": 21.9,
 "asian": 7.5,
 "latinx": 2.9,
 "below25k": 0.0,
 "median_income": 35855.0,
 "college": 54.2,
 "foreignborn": 20.4,
 "renteroccupied": 89.0,
 "last10yrs": 22.5,
 "vacancy": 11.7,
 "white_old": 81.4,
 "black_old": 17.2,
 "asian_old": 0.0,
 "latinx_old": 3.0,
 "below25k_old": 10.1,
 "median_income_old": 22970.57,
 "college_old": 53.2,
 "foreignborn_old": 26.8,
 "renteroccupied_old": 86.4,
 "last10yrs_old": 7.8999999999999995,
 "vacancy_old": 10.5,
 "professional": 75.6,
 "professional_old": 81.30000000000001,
 "travel_time": 21.4,
 "travel_time_old": 21.7,
 "new_residents": 64.4,
 "new_residents_old": 52.3,
 "non_english": 17.2,
 "non_english_old": 23.6,
 "avg_rent": 923.0,
 "avg_rent_old": 693.77
}